{
    "levelName": "",
    "gridSize": [
        10,
        10,
        5
    ],
    "objects": [
        {
            "type": "Wall",
            "position": [
                -1.5,
                0.5,
                3.0
            ],
            "scale": [
                2.0,
                0.5,
                1.0
            ]
        },
        {
            "type": "Box",
            "position": [
                -1.0,
                0.5,
                2.0
            ],
            "scale": [
                0.9900000095367432,
                1.0,
                0.9900000095367432
            ]
        },
        {
            "type": "Goal",
            "position": [
                -2.0,
                0.5,
                -1.0
            ],
            "scale": [
                1.0,
                0.5,
                1.0
            ]
        },
        {
            "type": "Pressure Plate",
            "position": [
                -1.0,
                0.05000000074505806,
                -1.0
            ],
            "scale": [
                0.8999999761581421,
                0.05000000074505806,
                0.8999999761581421
            ]
        },
        {
            "type": "Player",
            "position": [
                -2.0,
                0.25,
                1.0
            ],
            "scale": [
                1.0,
                1.0,
                1.0
            ]
        },
        {
            "type": "Ember Box",
            "position": [
                2.0,
                0.5,
                1.0
            ],
            "scale": [
                0.9900000095367432,
                1.0,
                0.9900000095367432
            ]
        },
        {
            "type": "Ember Box",
            "position": [
                2.0,
                0.5,
                -1.0
            ],
            "scale": [
                0.9900000095367432,
                1.0,
                0.9900000095367432
            ]
        },
        {
            "type": "Ember Box",
            "position": [
                2.0,
                0.5,
                0.0
            ],
            "scale": [
                0.9900000095367432,
                1.0,
                0.9900000095367432
            ]
        },
        {
            "type": "Volt Box",
            "position": [
                4.0,
                0.5,
                1.0
            ],
            "scale": [
                0.9900000095367432,
                1.0,
                0.9900000095367432
            ]
        },
        {
            "type": "Volt Box",
            "position": [
                1.0,
                0.5,
                2.0
            ],
            "scale": [
                0.9900000095367432,
                1.0,
                0.9900000095367432
            ]
        },
        {
            "type": "Volt Box",
            "position": [
                1.0,
                0.5,
                1.0
            ],
            "scale": [
                0.9900000095367432,
                1.0,
                0.9900000095367432
            ]
        },
        {
            "type": "Volt Box",
            "position": [
                1.0,
                0.5,
                0.0
            ],
            "scale": [
                0.9900000095367432,
                1.0,
                0.9900000095367432
            ]
        },
        {
            "type": "Volt Box",
            "position": [
                3.0,
                0.5,
                0.0
            ],
            "scale": [
                0.9900000095367432,
                1.0,
                0.9900000095367432
            ]
        },
        {
            "type": "Frost Box",
            "position": [
                -2.0,
                0.5,
                2.0
            ],
            "scale": [
                0.9900000095367432,
                1.0,
                0.9900000095367432
            ]
        },
        {
            "type": "Frost Box",
            "position": [
                2.0,
                0.5,
                2.0
            ],
            "scale": [
                0.9900000095367432,
                1.0,
                0.9900000095367432
            ]
        },
        {
            "type": "Magnet Box",
            "position": [
                1.0,
                0.5,
                -2.0
            ],
            "scale": [
                0.9900000095367432,
                1.0,
                0.9900000095367432
            ]
        },
        {
            "type": "Metal Box",
            "position": [
                7.0,
                0.5,
                -2.0
            ],
            "scale": [
                0.9900000095367432,
                1.0,
                0.9900000095367432
            ]
        }
    ]
}